rizomath/__init__.py
rizomath/cuboid.py
rizomath/interval.py
rizoma_utils-0.0.1.dist-info/LICENSE
rizoma_utils-0.0.1.dist-info/METADATA
rizoma_utils-0.0.1.dist-info/WHEEL
rizoma_utils-0.0.1.dist-info/top_level.txt
rizoma_utils-0.0.1.dist-info/RECORD
