Metadata-Version: 2.1
Name: rizoma-utils
Version: 0.0.1
Summary: Various personal utilites, mostly for Advent of Code
Home-page: https://github.com/jolitti/rizoma-utils
Author: rizoma
Author-email: aspirantecrittografo@gmail.com
License: UNKNOWN
Project-URL: Bug Tracker, https://github.com/jolitti/rizoma-utils/issues
Platform: UNKNOWN
Classifier: Development Status :: 1 - Planning
Classifier: Programming Language :: Python :: 3
Classifier: License :: OSI Approved :: MIT License
Classifier: Operating System :: OS Independent
Requires-Python: >=3.6
License-File: LICENSE
